knowledge_repo/__init__.py
knowledge_repo/_version.py
knowledge_repo/config.py
knowledge_repo/config_defaults.py
knowledge_repo/constants.py
knowledge_repo/converter.py
knowledge_repo/mapping.py
knowledge_repo/post.py
knowledge_repo/postprocessor.py
knowledge_repo/repository.py
knowledge_repo/app/__init__.py
knowledge_repo/app/app.py
knowledge_repo/app/auth_provider.py
knowledge_repo/app/config_defaults.py
knowledge_repo/app/index.py
knowledge_repo/app/models.py
knowledge_repo/app/permissions.py
knowledge_repo/app/proxies.py
knowledge_repo/app/roles.py
knowledge_repo/app/auth_providers/__init__.py
knowledge_repo/app/auth_providers/debug.py
knowledge_repo/app/auth_providers/ldap.py
knowledge_repo/app/auth_providers/oauth2.py
knowledge_repo/app/deploy/__init__.py
knowledge_repo/app/deploy/common.py
knowledge_repo/app/deploy/flask.py
knowledge_repo/app/deploy/gunicorn.py
knowledge_repo/app/deploy/uwsgi.py
knowledge_repo/app/migrations/alembic.ini
knowledge_repo/app/migrations/env.py
knowledge_repo/app/migrations/script.py.mako
knowledge_repo/app/migrations/versions/009eafe4838f_add_support_for_external_authentication.py
knowledge_repo/app/migrations/versions/1b385158fd32_assoc_rename_and_uuid_column.py
knowledge_repo/app/migrations/versions/36baffc5df12_add_groups_permissions_to_posts.py
knowledge_repo/app/migrations/versions/38eeba774226_resize_email_text.py
knowledge_repo/app/migrations/versions/40dfdcb2b07c_initial_version.py
knowledge_repo/app/migrations/versions/860cb49889a9_add_index_metadata_table_for_on_demand_.py
knowledge_repo/app/migrations/versions/9715822acf6c_add_errorlog_table.py
knowledge_repo/app/migrations/versions/d15f6cac07e1_add_subtitle_field_to_post_database.py
knowledge_repo/app/migrations/versions/eb39ac93fc39_add_pageview_indexes.py
knowledge_repo/app/routes/__init__.py
knowledge_repo/app/routes/auth.py
knowledge_repo/app/routes/comment.py
knowledge_repo/app/routes/debug.py
knowledge_repo/app/routes/editor.py
knowledge_repo-0.9.3.dist-info/LICENSE
knowledge_repo-0.9.3.dist-info/METADATA
knowledge_repo-0.9.3.dist-info/WHEEL
knowledge_repo-0.9.3.dist-info/top_level.txt
knowledge_repo-0.9.3.dist-info/RECORD
