Metadata-Version: 2.1
Name: knowledge-repo
Version: 0.9.3
Summary: A workflow for contributing company knowledge, in the form  of RMarkdowns, iPythons, and Markdowns, rendered and organized to magnify research impact across teams and time 
Author: 
Author-email: 
Classifier: Development Status :: 4 - Beta
Classifier: Environment :: Console
Classifier: Environment :: Web Environment
Classifier: Intended Audience :: Developers
Classifier: Intended Audience :: Information Technology
Classifier: Intended Audience :: Science/Research
Classifier: License :: OSI Approved :: Apache Software License
Classifier: Programming Language :: Python :: 3.7
Classifier: Programming Language :: Python :: 3.8
Classifier: Programming Language :: Python :: 3.9
License-File: LICENSE
Requires-Dist: pyyaml (==6.0)
Requires-Dist: markdown (==3.3.4)
Requires-Dist: pygments (==2.10.0)
Requires-Dist: gitpython (==3.1.18)
Requires-Dist: tabulate (==0.8.9)
Requires-Dist: cooked-input
Requires-Dist: requests
Requires-Dist: ipython-genutils
Requires-Dist: multiprocess
Requires-Dist: importlib-metadata (<=4.13.0)
Requires-Dist: flask (<=2.1.2)
Requires-Dist: flask-login (<=0.6.1)
Requires-Dist: flask-principal
Requires-Dist: flask-mail
Requires-Dist: Flask-Migrate
Requires-Dist: sqlalchemy (==1.4.37)
Requires-Dist: jinja2 (<=3.0.3,>=2.7)
Requires-Dist: werkzeug (<=2.0.3,>=1.0)
Requires-Dist: gunicorn
Requires-Dist: inflection
Requires-Dist: pillow
Requires-Dist: weasyprint (==54.3)
Requires-Dist: gcloud (==0.18.3)
Requires-Dist: botocore (==1.29.37)
Requires-Dist: boto3 (==1.26.37)
Requires-Dist: s3path (==0.3.4)
Requires-Dist: notion-client (==2.0.0)
Provides-Extra: all
Requires-Dist: nbformat ; extra == 'all'
Requires-Dist: nbconvert[execute] (<6.0.0) ; extra == 'all'
Requires-Dist: traitlets ; extra == 'all'
Requires-Dist: PyPDF2 (==2.1.1) ; extra == 'all'
Requires-Dist: wand (==0.6.7) ; extra == 'all'
Requires-Dist: requests-oauthlib ; extra == 'all'
Requires-Dist: ldap3 ; extra == 'all'
Requires-Dist: beautifulsoup4 ; extra == 'all'
Requires-Dist: coverage ; extra == 'all'
Requires-Dist: nose ; extra == 'all'
Requires-Dist: pep8 ; extra == 'all'
Requires-Dist: pycodestyle ; extra == 'all'
Provides-Extra: dev
Requires-Dist: beautifulsoup4 ; extra == 'dev'
Requires-Dist: coverage ; extra == 'dev'
Requires-Dist: nose ; extra == 'dev'
Requires-Dist: pep8 ; extra == 'dev'
Requires-Dist: pycodestyle ; extra == 'dev'
Provides-Extra: ipynb
Requires-Dist: nbformat ; extra == 'ipynb'
Requires-Dist: nbconvert[execute] (<6.0.0) ; extra == 'ipynb'
Requires-Dist: traitlets ; extra == 'ipynb'
Provides-Extra: ldap
Requires-Dist: ldap3 ; extra == 'ldap'
Provides-Extra: oauth
Requires-Dist: requests-oauthlib ; extra == 'oauth'
Provides-Extra: pdf
Requires-Dist: PyPDF2 (==2.1.1) ; extra == 'pdf'
Requires-Dist: wand (==0.6.7) ; extra == 'pdf'
